rayml.cpython-313-aarch64-linux-gnu.so
rayml-0.2.21.dist-info/METADATA
rayml-0.2.21.dist-info/WHEEL
rayml-0.2.21.dist-info/top_level.txt
rayml-0.2.21.dist-info/RECORD
rayml-0.2.21.dist-info/licenses/LICENSE
